{"chunk_definitions":[{"chunk_id":"cvrukpcc4mxts","chunk_label":"code2","document_id":"F6CBEFE2","expansion_state":0,"options":{"echo":true,"engine":"r","include":true,"label":"code2","message":false,"warning":false},"row":85,"row_count":1,"visible":true},{"chunk_id":"c6mijh36y2zaw","chunk_label":"code3","document_id":"F6CBEFE2","expansion_state":0,"options":{"echo":true,"engine":"r","include":true,"label":"code3","message":true,"warning":false},"row":112,"row_count":1,"visible":true},{"chunk_id":"cerh1irjho9y3","chunk_label":"code4","document_id":"F6CBEFE2","expansion_state":0,"options":{"echo":true,"engine":"r","include":true,"label":"code4","message":true,"warning":false},"row":141,"row_count":1,"visible":true}],"doc_write_time":1582450625}